advssdk/acquisition.cp311-win_amd64.pyd
advssdk/acquisition.pyi
advssdk/advs.cp311-win_amd64.pyd
advssdk/advs.pyi
advssdk/axi.cp311-win_amd64.pyd
advssdk/axi.pyi
advssdk/bias.cp311-win_amd64.pyd
advssdk/bias.pyi
advssdk/board.cp311-win_amd64.pyd
advssdk/board.pyi
advssdk/chip.cp311-win_amd64.pyd
advssdk/chip.pyi
advssdk/configuration.cp311-win_amd64.pyd
advssdk/configuration.pyi
advssdk/context.cp311-win_amd64.pyd
advssdk/cooling.cp311-win_amd64.pyd
advssdk/cooling.pyi
advssdk/device_props.cp311-win_amd64.pyd
advssdk/device_props.pyi
advssdk/errors.cp311-win_amd64.pyd
advssdk/errors.pyi
advssdk/extsync.cp311-win_amd64.pyd
advssdk/extsync.pyi
advssdk/hw_version.cp311-win_amd64.pyd
advssdk/hw_version.pyi
advssdk/monitor.cp311-win_amd64.pyd
advssdk/monitor.pyi
advssdk/nvmem.cp311-win_amd64.pyd
advssdk/nvmem.pyi
advssdk/py.typed
advssdk/trigger.cp311-win_amd64.pyd
advssdk/trigger.pyi
advssdk/__init__.py
advssdkpy-1.1.0.dist-info/DELVEWHEEL
advssdkpy-1.1.0.dist-info/METADATA
advssdkpy-1.1.0.dist-info/RECORD
advssdkpy-1.1.0.dist-info/top_level.txt
advssdkpy-1.1.0.dist-info/WHEEL
advssdkpy.libs/AdvsSdk-515288886677a0c2d25b9d4a0251b15e.dll
advssdkpy.libs/msvcp140-143b48ea0caba995ca490e7ab8b414d0.dll
advssdkpy.libs/msvcp140_atomic_wait-6385b3bfcb884ca89ba737f375c52d82.dll
advssdkpy.libs/tbb12-99f74eb25d5286aec1ada96b62d88698.dll
advssdkpy.libs/tbbmalloc-a02db7cab99c1dcd4b7dcb55c8334550.dll
advssdkpy.libs/tbbmalloc_proxy-38719cc05af80464cc61bc6d8a03c8a9.dll
licenses/__init__.py
licenses/base64/LICENSE
licenses/cpp-sort/LICENSE.txt
licenses/cpp-sort/NOTICE.txt
licenses/fmt/LICENSE
licenses/loguru/LICENSE
licenses/onetbb/LICENSE.txt
licenses/onetbb/NOTICE.txt
licenses/pugixml/LICENSE
licenses/spscqueue/LICENSE
licenses/unordered_dense/LICENSE
