Metadata-Version: 2.4
Name: advssdkpy
Version: 1.1.0
Summary: Python SDK for AdvaScope devices
Project-URL: documentation, https://advascope.gitlab.io/sdk/advssdkdocs/
Project-URL: homepage, https://advascope.cz/
Project-URL: download, https://pypi.org/project/advssdkpy/#files
Keywords: Advascope,AdvsSdkPy
Classifier: Intended Audience :: Science/Research
Classifier: Intended Audience :: Developers
Classifier: Programming Language :: Python :: 3.11
Classifier: Programming Language :: Python :: 3.12
Classifier: Programming Language :: Python :: 3.13
Classifier: Programming Language :: Python :: 3.14
Classifier: Topic :: Software Development
Classifier: Topic :: Scientific/Engineering
Classifier: Operating System :: Microsoft :: Windows
Classifier: Operating System :: Unix
Requires-Python: >=3.11
Requires-Dist: numpy>=2.4.1
